reisen.py
app/__init__.py
app/__main__.py
app/newAnimeEpisodes.py
generate/__init__.py
generate/commands.py
generate/reisen_exec.py
organize/__init__.py
organize/commands.py
Reisen-0.4.0.dist-info/LICENSE
Reisen-0.4.0.dist-info/METADATA
Reisen-0.4.0.dist-info/WHEEL
Reisen-0.4.0.dist-info/entry_points.txt
Reisen-0.4.0.dist-info/top_level.txt
Reisen-0.4.0.dist-info/RECORD
