Metadata-Version: 2.1
Name: Reisen
Version: 0.4.0
Summary: CLI tool to parse & move media files in a folder to another folder
Home-page: https://github.com/joeypoyiwu/anime-video-file-renamer-and-mover
Author: Joey Wu
Author-email: joeywu99@gmail.com
License: MIT
Platform: UNKNOWN
Classifier: Programming Language :: Python :: 3.9
Classifier: Operating System :: OS Independent
Requires-Python: >=3.6
License-File: LICENSE
Requires-Dist: click (==8.0.3)
Requires-Dist: pathlib (==1.0.1)
Requires-Dist: pyinstaller (==4.6)
Requires-Dist: pyinstaller-hooks-contrib (==2021.3)
Requires-Dist: termcolor (==1.1.0)
